sphinx_helm/__init__.py
sphinx_helm/_version.py
sphinx_helm/const.py
sphinx_helm/ext.py
sphinx_helm/gen.py
sphinx_helm/utils.py
sphinx_helm/templates/base.jinja2
sphinx_helm/templates/html.jinja2
sphinx_helm/templates/markdown.jinja2
sphinx_helm/templates/rst.jinja2
sphinx_helm/tests/test_extension.py
sphinx_helm/tests/mockcharts/deps/.helmignore
sphinx_helm/tests/mockcharts/deps/Chart.yaml
sphinx_helm/tests/mockcharts/deps/EXAMPLE.md
sphinx_helm/tests/mockcharts/deps/README.md
sphinx_helm/tests/mockcharts/deps/values.yaml
sphinx_helm/tests/mockcharts/deps/charts/simple-0.1.0.tgz
sphinx_helm/tests/mockcharts/deps/templates/NOTES.txt
sphinx_helm/tests/mockcharts/deps/templates/_helpers.tpl
sphinx_helm/tests/mockcharts/deps/templates/deployment.yaml
sphinx_helm/tests/mockcharts/deps/templates/ingress.yaml
sphinx_helm/tests/mockcharts/deps/templates/service.yaml
sphinx_helm/tests/mockcharts/deps/templates/tests/test-connection.yaml
sphinx_helm/tests/mockcharts/simple/.helmignore
sphinx_helm/tests/mockcharts/simple/Chart.yaml
sphinx_helm/tests/mockcharts/simple/README.md
sphinx_helm/tests/mockcharts/simple/values.yaml
sphinx_helm/tests/mockcharts/simple/templates/NOTES.txt
sphinx_helm/tests/mockcharts/simple/templates/_helpers.tpl
sphinx_helm/tests/mockcharts/simple/templates/deployment.yaml
sphinx_helm/tests/mockcharts/simple/templates/ingress.yaml
sphinx_helm/tests/mockcharts/simple/templates/service.yaml
sphinx_helm/tests/mockcharts/simple/templates/tests/test-connection.yaml
sphinx_helm-0.2.1.dist-info/METADATA
sphinx_helm-0.2.1.dist-info/WHEEL
sphinx_helm-0.2.1.dist-info/licenses/LICENSE
sphinx_helm-0.2.1.dist-info/RECORD
